mustopt/__about__.py
mustopt/__init__.py
mustopt/_container.py
mustopt/_errors.py
mustopt/_meta.py
mustopt/py.typed
mustopt-1.0.1.dist-info/METADATA
mustopt-1.0.1.dist-info/WHEEL
mustopt-1.0.1.dist-info/licenses/LICENSE
mustopt-1.0.1.dist-info/RECORD
