Metadata-Version: 2.3
Name: mustopt
Version: 1.0.1
Dynamic: Summary
Project-URL: Home, https://github.com/MemberWave/MustOpt
Project-URL: Issues, https://github.com/MemberWave/MustOpt/issues
Project-URL: Source, https://github.com/MemberWave/MustOpt
Author-email: Dmitry Starov <dmitry.staroff@gmail.com>
License: MIT License
License-File: LICENSE
Keywords: container,optional,typed
Classifier: Development Status :: 4 - Beta
Classifier: Programming Language :: Python
Classifier: Programming Language :: Python :: 3.7
Classifier: Programming Language :: Python :: 3.8
Classifier: Programming Language :: Python :: 3.9
Classifier: Programming Language :: Python :: 3.10
Classifier: Programming Language :: Python :: 3.11
Classifier: Programming Language :: Python :: 3.12
Classifier: Programming Language :: Python :: Implementation :: CPython
Classifier: Programming Language :: Python :: Implementation :: PyPy
Classifier: Typing :: Typed
Requires-Python: >=3.7
